Metadata-Version: 2.1
Name: languager
Version: 1.0.0
Summary: ISO639 Language Service
Home-page: https://github.com/joniumGit/languager
Author: joniumGit
License: UNKNOWN
Project-URL: Bug Reports, https://github.com/joniumGit/languager
Project-URL: Source, https://github.com/joniumGit/languager
Keywords: ISO639,languages,localization,server
Platform: UNKNOWN
Classifier: Development Status :: 4 - Beta
Classifier: Intended Audience :: Developers
Classifier: License :: OSI Approved :: MIT License
Classifier: Programming Language :: Python :: 3
Classifier: Topic :: Software Development :: Localization
Requires-Python: >=3.8
Provides-Extra: test
License-File: LICENSE
